b_aws_cdk_parallel/__init__.py
b_aws_cdk_parallel/aws_cdk_stack.py
b_aws_cdk_parallel/cdk_arguments.py
b_aws_cdk_parallel/cdk_synth.py
b_aws_cdk_parallel/color_print.py
b_aws_cdk_parallel/deploy_command.py
b_aws_cdk_parallel/deployment_executor.py
b_aws_cdk_parallel/deployment_type.py
b_aws_cdk_parallel/print_colors.py
b_aws_cdk_parallel/stack_dependencies.py
b_aws_cdk_parallel/cli/__init__.py
b_aws_cdk_parallel/cli/acdk.py
b_aws_cdk_parallel_test/integration/__init__.py
b_aws_cdk_parallel_test/integration/infrastructure/__init__.py
b_aws_cdk_parallel_test/integration/infrastructure/infrastructure1/__init__.py
b_aws_cdk_parallel_test/integration/infrastructure/infrastructure1/app.py
b_aws_cdk_parallel_test/integration/infrastructure/infrastructure1/main_stack.py
b_aws_cdk_parallel_test/integration/infrastructure/infrastructure2/__init__.py
b_aws_cdk_parallel_test/integration/infrastructure/infrastructure2/app.py
b_aws_cdk_parallel_test/integration/infrastructure/infrastructure2/main_stack.py
b_aws_cdk_parallel_test/integration/infrastructure/infrastructure3/__init__.py
b_aws_cdk_parallel_test/integration/infrastructure/infrastructure3/app.py
b_aws_cdk_parallel_test/integration/infrastructure/infrastructure3/main_stack.py
b_aws_cdk_parallel_test/integration/infrastructure/infrastructure3/stack1.py
b_aws_cdk_parallel_test/integration/infrastructure/infrastructure3/stack10.py
b_aws_cdk_parallel_test/integration/infrastructure/infrastructure3/stack2.py
b_aws_cdk_parallel_test/integration/infrastructure/infrastructure3/stack3.py
b_aws_cdk_parallel_test/integration/infrastructure/infrastructure3/stack4.py
b_aws_cdk_parallel_test/integration/infrastructure/infrastructure3/stack5.py
b_aws_cdk_parallel_test/integration/infrastructure/infrastructure3/stack6.py
b_aws_cdk_parallel_test/integration/infrastructure/infrastructure3/stack7.py
b_aws_cdk_parallel_test/integration/infrastructure/infrastructure3/stack8.py
b_aws_cdk_parallel-3.3.0.dist-info/LICENSE
b_aws_cdk_parallel-3.3.0.dist-info/METADATA
b_aws_cdk_parallel-3.3.0.dist-info/WHEEL
b_aws_cdk_parallel-3.3.0.dist-info/entry_points.txt
b_aws_cdk_parallel-3.3.0.dist-info/top_level.txt
b_aws_cdk_parallel-3.3.0.dist-info/RECORD
