Metadata-Version: 2.1
Name: b-aws-cdk-parallel
Version: 3.3.0
Summary: Package that enables deployment of AWS CDK stacks in parallel.
Home-page: https://github.com/biomapas/B.AwsCdkParallel.git
Author: Laimonas Sutkus
Author-email: laimonas.sutkus@biomapas.com
License: Apache License 2.0
Keywords: AWS IAC CDK Parallel
Platform: UNKNOWN
Classifier: Programming Language :: Python :: 3
Classifier: Operating System :: OS Independent
Requires-Dist: b-continuous-subprocess (<1.0.0,>=0.3.2)
